snakenv/__init__.py
snakenv/__main__.py
snakenv-1.2.1.dist-info/METADATA
snakenv-1.2.1.dist-info/WHEEL
snakenv-1.2.1.dist-info/entry_points.txt
snakenv-1.2.1.dist-info/top_level.txt
snakenv-1.2.1.dist-info/RECORD
