Metadata-Version: 2.1
Name: snakenv
Version: 1.2.1
Summary: Use env variables in python
Home-page: https://github.com/yunisdev/snakenv
Author: yunisdev
Author-email: yunisdev.04@gmail.com
License: UNKNOWN
Platform: UNKNOWN
Classifier: Programming Language :: Python :: 3
Classifier: License :: OSI Approved :: MIT License
Classifier: Operating System :: OS Independent
Classifier: Topic :: Software Development
Classifier: Natural Language :: English
Requires-Python: >=3.6
Requires-Dist: click
Requires-Dist: python-dotenv
